pollination/honeybee_display/__init__.py
pollination/honeybee_display/abnt.py
pollination/honeybee_display/translate.py
pollination/honeybee_display/scripts/abnt_nbr_15575_visualization.py
pollination_honeybee_display-0.1.19.dist-info/LICENSE
pollination_honeybee_display-0.1.19.dist-info/METADATA
pollination_honeybee_display-0.1.19.dist-info/WHEEL
pollination_honeybee_display-0.1.19.dist-info/top_level.txt
pollination_honeybee_display-0.1.19.dist-info/RECORD
