Metadata-Version: 2.1
Name: pollination-honeybee-display
Version: 0.1.19
Summary: Plugin for Pollination with all honeybee extensions.
Home-page: https://github.com/pollination/honeybee-display
Author: ladybug-tools
Author-email: info@ladybug.tools
Maintainer: chris, ladybug-tools
Maintainer-email: chris@ladybug.tools, info@ladybug.tools
License: PolyForm Shield License 1.0.0, https://polyformproject.org/wp-content/uploads/2020/06/PolyForm-Shield-1.0.0.txt
Project-URL: icon, https://raw.githubusercontent.com/ladybug-tools/artwork/master/icons_bugs/grasshopper_tabs/Honeybee.png
Project-URL: docker, https://hub.docker.com/r/ladybugtools/honeybee-display
Keywords: honeybee,display,vtk,ladybug-tools
License-File: LICENSE
Requires-Dist: pollination-dsl>=0.17.1
Requires-Dist: honeybee-display[full]>=0.5.3
